[
  {
    "question": "ما الذي يجذبك عادةً إلى أي نشاط؟",
    "options": [
      "التحدي",
      "الاسترخاء",
      "التفاعل مع الآخرين",
      "السرعة والإثارة",
      "التركيز الذهني"
    ],
    "multi": true,
    "free": true,
    "type": "multiple",
    "allow_custom": true
  },
  {
    "question": "ما نوع البيئة التي تفضلها أثناء التدريب أو الأنشطة؟",
    "options": [
      "الطبيعة المفتوحة",
      "مساحة داخلية منظمة",
      "أماكن مزدحمة ونشيطة",
      "أماكن هادئة وفارغة"
    ],
    "multi": true,
    "free": true,
    "type": "multiple",
    "allow_custom": true
  },
  {
    "question": "كيف تصف أسلوبك في اتخاذ القرارات؟",
    "options": [
      "سريع ومندفع",
      "تحليلي ومتأني",
      "أتبع حدسي",
      "غالبًا أستشير الآخرين"
    ],
    "multi": true,
    "free": true,
    "type": "multiple",
    "allow_custom": true
  },
  {
    "question": "كيف تتعامل مع الألم أو التعب؟",
    "options": [
      "أتجاهله وأواصل",
      "أحلل الوضع وأتأقلم",
      "أتوقف فورًا",
      "أتحمل وأكمل"
    ],
    "multi": true,
    "free": true,
    "type": "multiple",
    "allow_custom": true
  },
  {
    "question": "هل تفضل التعمق في شيء واحد أم استكشاف أشياء متعددة؟",
    "options": [
      "التعمق في شيء واحد",
      "استكشاف أشياء متعددة",
      "التوازن بين الاثنين"
    ],
    "multi": true,
    "free": true,
    "type": "multiple",
    "allow_custom": true
  }
]